LICENSE
MANIFEST.in
README
setup.cfg
setup.py
sphinxcontrib/operationdomain/__init__.py
sphinxcontrib/operationdomain/command.py
sphinxcontrib/operationdomain/core.py
sphinxcontrib/operationdomain/howto.py
sphinxcontrib/operationdomain/install.py
sphinxcontrib/operationdomain/reverse.py
sphinxcontrib/operationdomain/setting.py
sphinxcontrib_operationdomain.egg-info/PKG-INFO
sphinxcontrib_operationdomain.egg-info/SOURCES.txt
sphinxcontrib_operationdomain.egg-info/dependency_links.txt
sphinxcontrib_operationdomain.egg-info/not-zip-safe
sphinxcontrib_operationdomain.egg-info/requires.txt
sphinxcontrib_operationdomain.egg-info/top_level.txt