Metadata-Version: 1.1
Name: sphinxcontrib-operationdomain
Version: 0.1.2
Summary: Sphinx extension sphinxcontrib-operationdomain
Home-page: https://bitbucket.org/togakushi/sphinxcontrib-operationdomain
Author: togakushi
Author-email: nina.togakushi@gmail.com
License: BSD
Platform: any
Classifier: Development Status :: 4 - Beta
Classifier: Environment :: Console
Classifier: Environment :: Web Environment
Classifier: Intended Audience :: Developers
Classifier: License :: OSI Approved :: BSD License
Classifier: Operating System :: OS Independent
Classifier: Topic :: Documentation
Classifier: Topic :: Utilities
